NetkillerManagementFix1/README.md
NetkillerManagementFix1/__init__.py
NetkillerManagementFix1/__main__.py
NetkillerManagementFix1/file.epub
NetkillerManagementFix1/index.html
NetkillerManagementFix1/css/__init__.py
NetkillerManagementFix1/css/annotations.css
NetkillerManagementFix1/css/main.css
NetkillerManagementFix1/css/normalize.css
NetkillerManagementFix1/css/popup.css
NetkillerManagementFix1/font/__init__.py
NetkillerManagementFix1/font/fontello.eot
NetkillerManagementFix1/font/fontello.svg
NetkillerManagementFix1/font/fontello.ttf
NetkillerManagementFix1/font/fontello.woff
NetkillerManagementFix1/img/__init__.py
NetkillerManagementFix1/img/annotator-glyph-sprite.png
NetkillerManagementFix1/img/annotator-icon-sprite.png
NetkillerManagementFix1/img/apple-touch-icon.png
NetkillerManagementFix1/img/cancelfullscreen.png
NetkillerManagementFix1/img/close.png
NetkillerManagementFix1/img/fullscreen.png
NetkillerManagementFix1/img/loader.gif
NetkillerManagementFix1/img/menu-icon.png
NetkillerManagementFix1/img/save.png
NetkillerManagementFix1/img/saved.png
NetkillerManagementFix1/img/settings-s.png
NetkillerManagementFix1/img/settings.png
NetkillerManagementFix1/img/star.png
NetkillerManagementFix1/js/__init__.py
NetkillerManagementFix1/js/epub.js
NetkillerManagementFix1/js/epub.min.js
NetkillerManagementFix1/js/epub.min.map
NetkillerManagementFix1/js/hooks.min.js
NetkillerManagementFix1/js/hooks.min.map
NetkillerManagementFix1/js/reader.js
NetkillerManagementFix1/js/reader.js.map
NetkillerManagementFix1/js/reader.min.js
NetkillerManagementFix1/js/reader.min.map
NetkillerManagementFix1/js/hooks/__init__.py
NetkillerManagementFix1/js/hooks/extensions/__init__.py
NetkillerManagementFix1/js/hooks/extensions/highlight.js
NetkillerManagementFix1/js/libs/__init__.py
NetkillerManagementFix1/js/libs/jquery.min.js
NetkillerManagementFix1/js/libs/localforage.min.js
NetkillerManagementFix1/js/libs/screenfull.js
NetkillerManagementFix1/js/libs/screenfull.min.js
netkiller_management_fix1-2025.3.24.1.dist-info/METADATA
netkiller_management_fix1-2025.3.24.1.dist-info/WHEEL
netkiller_management_fix1-2025.3.24.1.dist-info/entry_points.txt
netkiller_management_fix1-2025.3.24.1.dist-info/top_level.txt
netkiller_management_fix1-2025.3.24.1.dist-info/RECORD
